{
  "project_info": {
    "project_number": "733799275863",
    "firebase_url": "https://biblioteca-68bbc-default-rtdb.firebaseio.com",
    "project_id": "biblioteca-68bbc",
    "storage_bucket": "biblioteca-68bbc.firebasestorage.app"
  },
  "client": [
    {
      "client_info": {
        "mobilesdk_app_id": "1:733799275863:android:9fc4d80b8ef529e81cf212",
        "android_client_info": {
          "package_name": "com.example.ud.biblioteca"
        }
      },
      "oauth_client": [],
      "api_key": [
        {
          "current_key": "AIzaSyDQN-tnC37cdVWPbNU3BfzoA8yNMnCkSVI"
        }
      ],
      "services": {
        "appinvite_service": {
          "other_platform_oauth_client": []
        }
      }
    }
  ],
  "configuration_version": "1"
}